DiSwarm/__init__.py
DiSwarm/_interface.py
DiSwarm/keydet.py
DiSwarm-2.2.0.dist-info/LICENSE
DiSwarm-2.2.0.dist-info/METADATA
DiSwarm-2.2.0.dist-info/WHEEL
DiSwarm-2.2.0.dist-info/top_level.txt
DiSwarm-2.2.0.dist-info/RECORD
