Metadata-Version: 2.1
Name: DiSwarm
Version: 2.2.0
Summary: Discord-based Swarm Protocol Library
Home-page: https://github.com/iTecAI/DiSwarm
Author: iTecX
Author-email: matteovh@gmail.com
License: UNKNOWN
Platform: UNKNOWN
Classifier: Programming Language :: Python :: 3
Classifier: License :: OSI Approved :: MIT License
Classifier: Operating System :: OS Independent
Requires-Dist: discord
Requires-Dist: cryptography
